flake8_numba/__init__.py
flake8_numba/plugin.py
flake8_numba/rule.py
flake8_numba/rules/__init__.py
flake8_numba/rules/nba0.py
flake8_numba/rules/nba1.py
flake8_numba/rules/nba2.py
flake8_numba/utils.py
flake8_numba/visitor.py
flake8_numba-0.4.0.dist-info/entry_points.txt
flake8_numba-0.4.0.dist-info/METADATA
flake8_numba-0.4.0.dist-info/WHEEL
flake8_numba-0.4.0.dist-info/RECORD
