Metadata-Version: 2.1
Name: flake8-numba
Version: 0.4.0
Summary: Perform checks over numba usage
Author: Manuel Floriano Vázquez
Author-email: mflovaa@gmail.com
Requires-Python: >=3.9,<4.0
Classifier: Programming Language :: Python :: 3
Classifier: Programming Language :: Python :: 3.9
Classifier: Programming Language :: Python :: 3.10
Classifier: Programming Language :: Python :: 3.11
Requires-Dist: numba
